emojihash/__init__.py
emojihash/main.py
emojihash/db/__init__.py
emojihash/db/basic_emojis.py
emojihash/hash_classes/__init__.py
emojihash/hash_classes/eh1.py
emojihash/typing/__init__.py
emojihash/typing/basic_types.py
emojihash-0.1.1.dist-info/LICENSE
emojihash-0.1.1.dist-info/METADATA
emojihash-0.1.1.dist-info/WHEEL
emojihash-0.1.1.dist-info/top_level.txt
emojihash-0.1.1.dist-info/RECORD
