Metadata-Version: 2.1
Name: emojihash
Version: 0.1.1
Summary: Emoji hash functions
Home-page: https://github.com/v1a0/sqllex
Author: v1a0
Author-email: contact@v1a0.dev
License: gpl-3.0
Download-URL: https://github.com/V1A0/emojihash/archive/refs/tags/v0.1.1.tar.gz
Keywords: emoji,crypto,security,cryptography,hash,sha,sha512,sha256,md5,fun
Platform: UNKNOWN
Classifier: Development Status :: 3 - Alpha
Classifier: Intended Audience :: Developers
Classifier: Topic :: Security :: Cryptography
Classifier: License :: OSI Approved :: GNU General Public License v3 (GPLv3)
Classifier: Programming Language :: Python :: 3.9
License-File: LICENSE
